nqviz/__init__.py
nqviz/board.py
nqviz/n_queen.py
nqviz-0.0.6.dist-info/METADATA
nqviz-0.0.6.dist-info/WHEEL
nqviz-0.0.6.dist-info/top_level.txt
nqviz-0.0.6.dist-info/RECORD
