Metadata-Version: 2.1
Name: nqviz
Version: 0.0.6
Summary: N Queen Visualizer
Home-page: https://github.com/jhan15/nqviz
Author: Jianming Han
Author-email: hjma810@126.com
License: MIT
Platform: UNKNOWN
Classifier: Development Status :: 4 - Beta
Classifier: License :: OSI Approved :: MIT License
Classifier: Programming Language :: Python :: 3.8
Requires-Python: >=3
Requires-Dist: pygame (>=2.0.1)
